dispest/demod.py
pyusel_dispest-0.0.1.dist-info/LICENSE
pyusel_dispest-0.0.1.dist-info/METADATA
pyusel_dispest-0.0.1.dist-info/WHEEL
pyusel_dispest-0.0.1.dist-info/top_level.txt
pyusel_dispest-0.0.1.dist-info/RECORD
