Metadata-Version: 2.1
Name: pyusel-dispest
Version: 0.0.1
Summary: Displacement estimation tools for use in ultrasound elasticity imaging
Author: Wren Wightman
Author-email: Wren Wightman <wren.wightman@duke.edu>
Project-URL: Homepage, https://github.com/wewightman/dispest
Classifier: Programming Language :: Python :: 3
Classifier: License :: OSI Approved :: MIT License
Classifier: Operating System :: OS Independent
Requires-Python: >=3.7
License-File: LICENSE
